{"showLegend":true,"visibility":true,"opacity":1,"layers":[{"layerDefinition":{"geometryType":"esriGeometryPoint","objectIdField":"__OBJECTID","type":"Feature Layer","drawingInfo":{"renderer":{"type":"simple","symbol":{"color":[115,38,0,237],"size":7.5,"angle":0,"xoffset":0,"yoffset":0,"type":"esriSMS","style":"esriSMSCircle","outline":{"color":[0,0,128,255],"width":0.9975,"type":"esriSLS","style":"esriSLSSolid"}}},"fixedSymbols":true},"fields":[{"name":"__OBJECTID","alias":"__OBJECTID","type":"esriFieldTypeOID","editable":false,"nullable":false,"domain":null},{"name":"Water_works","alias":"Water works","type":"esriFieldTypeString","length":255,"editable":true,"nullable":true,"domain":null},{"name":"Source","alias":"Source","type":"esriFieldTypeString","length":255,"editable":true,"nullable":true,"domain":null},{"name":"PFBS","alias":"PFBS","type":"esriFieldTypeDouble","editable":true,"nullable":true,"domain":null,"_final":1},{"name":"HFPO_DA","alias":"HFPO- DA","type":"esriFieldTypeDouble","editable":true,"nullable":true,"domain":null,"_final":1},{"name":"PFHpA","alias":"PFHpA","type":"esriFieldTypeDouble","editable":true,"nullable":true,"domain":null,"_final":1},{"name":"PFHxS","alias":"PFHxS","type":"esriFieldTypeDouble","editable":true,"nullable":true,"domain":null,"_final":1},{"name":"ADONA","alias":"ADONA","type":"esriFieldTypeInteger","editable":true,"nullable":true,"domain":null},{"name":"PFOA","alias":"PFOA","type":"esriFieldTypeDouble","editable":true,"nullable":true,"domain":null},{"name":"PFOS","alias":"PFOS","type":"esriFieldTypeDouble","editable":true,"nullable":true,"domain":null,"_final":1},{"name":"PFNA","alias":"PFNA","type":"esriFieldTypeInteger","editable":true,"nullable":true,"domain":null},{"name":"Total_PFAS","alias":"Total PFAS","type":"esriFieldTypeDouble","editable":true,"nullable":true,"domain":null},{"name":"Unit","alias":"Unit","type":"esriFieldTypeString","length":255,"editable":true,"nullable":true,"domain":null},{"name":"Latitude","alias":"Latitude","type":"esriFieldTypeDouble","editable":true,"nullable":true,"domain":null},{"name":"Longitude","alias":"Longitude","type":"esriFieldTypeDouble","editable":true,"nullable":true,"domain":null}],"capabilities":"Query,Editing,Extract","name":"gw sampled and detected","extent":{"xmin":-9912743.8101,"ymin":4446423.0799,"xmax":-9212089.8399,"ymax":4689294.9801,"spatialReference":{"wkid":102100}},"typeIdField":"","templates":[],"types":[],"minScale":73957191,"maxScale":0,"spatialReference":{"wkid":102100}},"featureSet":{"features":[{"geometry":{"x":-9468864.03,"y":4684204.93,"spatialReference":{"wkid":102100}},"attributes":{"Water_works":"Carroll Co WD-Ghent","Source":"GW","PFBS":0,"HFPO_DA":0,"PFHpA":0,"PFHxS":0,"ADONA":0,"PFOA":1.09,"PFOS":0,"PFNA":0,"Total_PFAS":1.09,"Unit":"ng/L","Latitude":38.73795395,"Longitude":-85.0602528,"__OBJECTID":0}},{"geometry":{"x":-9269628.25,"y":4664308.27,"spatialReference":{"wkid":102100}},"attributes":{"Water_works":"Vanceburg Electric Plant Board","Source":"GW","PFBS":0,"HFPO_DA":0,"PFHpA":0,"PFHxS":0,"ADONA":0,"PFOA":0,"PFOS":1.4,"PFNA":0,"Total_PFAS":1.4,"Unit":"ng/L","Latitude":38.59840196,"Longitude":-83.27048733,"__OBJECTID":1}},{"geometry":{"x":-9912743.81,"y":4446423.08,"spatialReference":{"wkid":102100}},"attributes":{"Water_works":"Barlow WTP","Source":"GW","PFBS":0,"HFPO_DA":0,"PFHpA":0,"PFHxS":1.62,"ADONA":0,"PFOA":0,"PFOS":0,"PFNA":0,"Total_PFAS":1.62,"Unit":"ng/L","Latitude":37.05247092,"Longitude":-89.04769268,"__OBJECTID":2}},{"geometry":{"x":-9691196.57,"y":4550115.19,"spatialReference":{"wkid":102100}},"attributes":{"Water_works":"Owensboro Mun Utilites - Cavin Plant","Source":"GW","PFBS":0,"HFPO_DA":0,"PFHpA":0,"PFHxS":0,"ADONA":0,"PFOA":2.13,"PFOS":0,"PFNA":0,"Total_PFAS":2.13,"Unit":"ng/L","Latitude":37.792222,"Longitude":-87.0575,"__OBJECTID":3}},{"geometry":{"x":-9212089.84,"y":4657337.25,"spatialReference":{"wkid":102100}},"attributes":{"Water_works":"Worthington Mun Water","Source":"GW","PFBS":2.1,"HFPO_DA":0,"PFHpA":0,"PFHxS":2.8,"ADONA":0,"PFOA":0,"PFOS":0,"PFNA":0,"Total_PFAS":4.9,"Unit":"ng/L","Latitude":38.549444,"Longitude":-82.753611,"__OBJECTID":4}},{"geometry":{"x":-9695525.67,"y":4547845.91,"spatialReference":{"wkid":102100}},"attributes":{"Water_works":"Owensboro Mun Utilities","Source":"GW","PFBS":0,"HFPO_DA":0,"PFHpA":0,"PFHxS":0,"ADONA":0,"PFOA":5.02,"PFOS":1.85,"PFNA":0,"Total_PFAS":6.87,"Unit":"ng/L","Latitude":37.776111,"Longitude":-87.096389,"__OBJECTID":5}},{"geometry":{"x":-9353001.72,"y":4689294.98,"spatialReference":{"wkid":102100}},"attributes":{"Water_works":"Augusta WTP","Source":"GW","PFBS":1.88,"HFPO_DA":0,"PFHpA":0,"PFHxS":0,"ADONA":0,"PFOA":4.43,"PFOS":1,"PFNA":0,"Total_PFAS":7.31,"Unit":"ng/L","Latitude":38.773611,"Longitude":-84.019444,"__OBJECTID":6}},{"geometry":{"x":-9591421.96,"y":4579317.55,"spatialReference":{"wkid":102100}},"attributes":{"Water_works":"Brandenburg Water Works","Source":"GW","PFBS":1.39,"HFPO_DA":0,"PFHpA":0,"PFHxS":2.49,"ADONA":0,"PFOA":1.72,"PFOS":3.01,"PFNA":0,"Total_PFAS":8.61,"Unit":"ng/L","Latitude":37.99923362,"Longitude":-86.16120942,"__OBJECTID":7}},{"geometry":{"x":-9533122.89,"y":4628396.27,"spatialReference":{"wkid":102100}},"attributes":{"Water_works":"Louisville Water Co Payne Plant","Source":"GW","PFBS":0,"HFPO_DA":4.42,"PFHpA":0,"PFHxS":0,"ADONA":0,"PFOA":4.31,"PFOS":1.34,"PFNA":0,"Total_PFAS":10.07,"Unit":"ng/L","Latitude":38.345833,"Longitude":-85.6375,"__OBJECTID":8}},{"geometry":{"x":-9236178.15,"y":4679899.3,"spatialReference":{"wkid":102100}},"attributes":{"Water_works":"South Shore","Source":"GW","PFBS":8.55,"HFPO_DA":0,"PFHpA":5.02,"PFHxS":11,"ADONA":0,"PFOA":23.2,"PFOS":18.9,"PFNA":0,"Total_PFAS":66.67,"Unit":"ng/L","Latitude":38.707778,"Longitude":-82.97,"__OBJECTID":9}}],"geometryType":"esriGeometryPoint"},"nextObjectId":10,"popupInfo":{"title":"","fieldInfos":[{"fieldName":"__OBJECTID","label":"__OBJECTID","isEditable":false,"tooltip":"","visible":false,"format":null,"stringFieldOption":"textbox"},{"fieldName":"Water_works","label":"Water works","isEditable":true,"tooltip":"","visible":true,"format":null,"stringFieldOption":"textbox"},{"fieldName":"Source","label":"Source","isEditable":true,"tooltip":"","visible":true,"format":null,"stringFieldOption":"textbox"},{"fieldName":"PFBS","label":"PFBS","isEditable":true,"tooltip":"","visible":true,"format":{"places":2,"digitSeparator":true},"stringFieldOption":"textbox"},{"fieldName":"HFPO_DA","label":"HFPO- DA","isEditable":true,"tooltip":"","visible":true,"format":{"places":2,"digitSeparator":true},"stringFieldOption":"textbox"},{"fieldName":"PFHpA","label":"PFHpA","isEditable":true,"tooltip":"","visible":true,"format":{"places":2,"digitSeparator":true},"stringFieldOption":"textbox"},{"fieldName":"PFHxS","label":"PFHxS","isEditable":true,"tooltip":"","visible":true,"format":{"places":2,"digitSeparator":true},"stringFieldOption":"textbox"},{"fieldName":"ADONA","label":"ADONA","isEditable":true,"tooltip":"","visible":true,"format":{"places":0,"digitSeparator":true},"stringFieldOption":"textbox"},{"fieldName":"PFOA","label":"PFOA","isEditable":true,"tooltip":"","visible":true,"format":{"places":2,"digitSeparator":true},"stringFieldOption":"textbox"},{"fieldName":"PFOS","label":"PFOS","isEditable":true,"tooltip":"","visible":true,"format":{"places":2,"digitSeparator":true},"stringFieldOption":"textbox"},{"fieldName":"PFNA","label":"PFNA","isEditable":true,"tooltip":"","visible":true,"format":{"places":0,"digitSeparator":true},"stringFieldOption":"textbox"},{"fieldName":"Total_PFAS","label":"Total PFAS","isEditable":true,"tooltip":"","visible":true,"format":{"places":2,"digitSeparator":true},"stringFieldOption":"textbox"},{"fieldName":"Unit","label":"Unit","isEditable":true,"tooltip":"","visible":true,"format":null,"stringFieldOption":"textbox"},{"fieldName":"Latitude","label":"Latitude","isEditable":true,"tooltip":"","visible":true,"format":{"places":2,"digitSeparator":true},"stringFieldOption":"textbox"},{"fieldName":"Longitude","label":"Longitude","isEditable":true,"tooltip":"","visible":true,"format":{"places":2,"digitSeparator":true},"stringFieldOption":"textbox"}],"description":null,"showAttachments":false,"mediaInfos":[]}}]}